[{"id": "R7fEEeJHQlI8xBKeK52V", "userId": "OWst8rT9GJNRuVUs94cWCL6srW92", "updatedAt": 1626235308116, "jobClass": "\uac00\uc218", "birthDate": "1992/11/23", "name": "\ubc15\uc131\uc5f0", "isApproved": true, "company": "\uc0dd\uac01\uc744\ubcf4\uc5ec\uc8fc\ub294\uc5d4\ud130\ud14c\uc778\uba3c\ud2b8", "groupName": "Rocket Punch", "bodyProfile": "O\ud615", "oldName": "", "createdAt": 1626235308116, "pictureCount": 0, "about": "", "image": "", "gender": false}, {"id": "S9tsfCJdExMTxb3cQ0hv", "groupName": "BAE173", "bodyProfile": "184cm, O\ud615, \uc0c1\uc758 100 \u2022 \ud558\uc758 29, \ubc1c \uc0ac\uc774\uc988 280mm", "jobClass": "\uac00\uc218", "isApproved": true, "name": "\ub3c4\ud604", "createdAt": 1626235308116, "gender": true, "about": "", "birthDate": "2004/11/10", "oldName": "", "company": "\ud3ec\ucf13\ub3cc\uc2a4\ud29c\ub514\uc624", "image": "", "pictureCount": 0, "userId": "OWst8rT9GJNRuVUs94cWCL6srW92", "updatedAt": 1626235308116}, {"id": "cZPrFTrYKVtGa51JlL87", "birthDate": "1989/08/21", "jobClass": "\uc2f1\uc5b4\uc1a1\ub77c\uc774\ud130", "oldName": "", "updatedAt": 1626235308116, "gender": true, "createdAt": 1626235308116, "isApproved": true, "company": "\uc1fc\ud50c\ub808\uc774", "about": "", "bodyProfile": "174~6cm, 265mm, O\ud615", "pictureCount": 0, "image": "", "userId": "OWst8rT9GJNRuVUs94cWCL6srW92", "name": "\uc774\uc2b9\uc724", "groupName": ""}, {"id": "xPTWcurkC68L6FxFSHer", "gender": true, "createdAt": 1626235308116, "bodyProfile": "184cm, 69kg, A\ud615, 260mm", "company": "\ud050\ube0c\uc5d4\ud130\ud14c\uc778\uba3c\ud2b8", "oldName": "", "isApproved": true, "jobClass": "\uac00\uc218", "userId": "OWst8rT9GJNRuVUs94cWCL6srW92", "updatedAt": 1626235308116, "image": "", "name": "\uc2e0\uc6d0", "birthDate": "1995/12/11", "about": "", "groupName": "\ud39c\ud0c0\uace4", "pictureCount": 0}, {"id": "1kCKlyOP1ESORN5eh2AB", "image": "https://touchizen.com/idolface/image/idolprofile/21_kangdaniel_wannaone/1.jpg", "oldName": "", "company": "\ucee4\ub125\ud2b8 \uc5d4\ud130\ud14c\uc778\uba3c\ud2b8", "createdAt": 1626235308116, "userId": "OWst8rT9GJNRuVUs94cWCL6srW92", "gender": true, "birthDate": "1996/12/10", "about": "", "pictureCount": 1, "groupName": "Wanna One", "isApproved": true, "updatedAt": 1626235308116, "bodyProfile": "181.5cm, 67kg, A\ud615, \uc0c1\uc758 105~110,\ud558\uc758 30, 280mm, 54.6cm", "name": "\uac15\ub2e4\ub2c8\uc5d8", "jobClass": "\uac00\uc218"}, {"id": "23ouQbZKQaHfWLPhsKxT", "birthDate": "2000/01/22", "userId": "OWst8rT9GJNRuVUs94cWCL6srW92", "groupName": "Fromis 9", "image": "https://touchizen.com/idolface/image/idolprofile/13_leeseoyeon_singer/1.jpg", "oldName": "", "jobClass": "\uac00\uc218", "name": "\uc774\uc11c\uc5f0", "isApproved": true, "about": "", "gender": false, "pictureCount": 1, "createdAt": 1626235308116, "updatedAt": 1626235308116, "company": "\uc624\ud504\ub354\ub808\ucf54\ub4dc \uc5d4\ud130\ud14c\uc778\uba3c\ud2b8", "bodyProfile": "158cm, 47kg, A\ud615"}, {"id": "9sDKIeocRP9yuhC9nquu", "userId": "OWst8rT9GJNRuVUs94cWCL6srW92", "gender": false, "image": "https://touchizen.com/idolface/image/idolprofile/04_dahyeon_rocketpunch/1.jpg", "bodyProfile": "164cm, 44~45kg, A\ud615, 235~240mm", "birthDate": "2005/04/29", "name": "\ub2e4\ud604", "about": "", "jobClass": "\uac00\uc218", "updatedAt": 1626235308116, "company": "\uc6b8\ub9bc \uc5d4\ud130\ud14c\uc778\uba3c\ud2b8", "groupName": "Rocket Punch", "oldName": "", "pictureCount": 1, "isApproved": true, "createdAt": 1626235308116}, {"id": "CK1ZGoHpTbvluJa20Ok8", "image": "https://touchizen.com/idolface/image/idolprofile/16_jangwonyoung_singer/1.jpg", "bodyProfile": "171cm, O\ud615, 245mm", "isApproved": true, "pictureCount": 1, "groupName": "", "updatedAt": 1626235308116, "company": "\uc2a4\ud0c0\uc27d \uc5d4\ud130\ud14c\uc778\uba3c\ud2b8", "birthDate": "2000/08/01", "gender": false, "userId": "OWst8rT9GJNRuVUs94cWCL6srW92", "oldName": "", "about": "", "name": "\uc7a5\uc6d0\uc601", "jobClass": "\uac00\uc218", "createdAt": 1626235308116}, {"id": "EWsodrnQmhn6VWQlsDn5", "bodyProfile": "175cm, 62kg, B\ud615, 250~260mm", "updatedAt": 1626235308116, "groupName": "Wanna One", "oldName": "", "pictureCount": 1, "jobClass": "\uac00\uc218", "gender": true, "image": "https://touchizen.com/idolface/image/idolprofile/31_younjisung_wannaone/1.jpg", "createdAt": 1626235308116, "name": "\uc724\uc9c0\uc131", "company": "LM \uc5d4\ud130\ud14c\uc778\uba3c\ud2b8", "about": "", "isApproved": true, "birthDate": "1991/03/08", "userId": "OWst8rT9GJNRuVUs94cWCL6srW92"}, {"id": "Eo7TkVVVLA2P8vVvBXsZ", "gender": true, "image": "https://touchizen.com/idolface/image/idolprofile/25_notaehyeon_jbj/1.jpg", "jobClass": "\uac00\uc218", "userId": "OWst8rT9GJNRuVUs94cWCL6srW92", "pictureCount": 1, "birthDate": "1993/10/15", "name": "\ub178\ud0dc\ud604", "updatedAt": 1626235308116, "groupName": "", "isApproved": true, "company": "\uc2a4\ud0c0\ud06c\ub8e8\uc774\uc5d4\ud2f0", "createdAt": 1626235308116, "about": "", "oldName": "", "bodyProfile": "168cm, 59kg, A\ud615"}, {"id": "FHfYTLOKhYRST5w1XrBe", "groupName": "Rocket Punch", "company": "\uc6b8\ub9bc \uc5d4\ud130\ud14c\uc778\uba3c\ud2b8", "createdAt": 1626235308116, "jobClass": "\uac00\uc218", "oldName": "", "isApproved": true, "image": "https://touchizen.com/idolface/image/idolprofile/17_jury_rocketpunch/1.jpg", "pictureCount": 1, "gender": false, "bodyProfile": "160cm, 44kg, A\ud615, 240mm", "name": "\uc96c\ub9ac", "userId": "OWst8rT9GJNRuVUs94cWCL6srW92", "birthDate": "1997/10/03", "about": "", "updatedAt": 1626235308116}, {"id": "HsMqghgpRZg8ylO3MHJg", "jobClass": "\uac00\uc218", "userId": "OWst8rT9GJNRuVUs94cWCL6srW92", "image": "https://touchizen.com/idolface/image/idolprofile/30_youngtak_singer/1.jpg", "name": "\uc601\ud0c1", "gender": true, "bodyProfile": "179cm, 64kg, O\ud615", "updatedAt": 1626235308116, "about": "", "pictureCount": 1, "company": "\ubc00\ub77c\uadf8\ub85c / \ub274\uc5d0\ub77c\ud504\ub85c\uc81d\ud2b8", "birthDate": "1983/05/13", "createdAt": 1626235308116, "groupName": "\ubc15\uc9c0, \uc5d8\ud074\ub808\uc2a4", "isApproved": true, "oldName": ""}, {"id": "I4lR1E1ccxj2POSX9urb", "gender": true, "updatedAt": 1626235308116, "isApproved": true, "jobClass": "\uac00\uc218", "image": "https://touchizen.com/idolface/image/idolprofile/22_kimyohan_wei/1.jpg", "name": "\uae40\uc694\ud55c", "createdAt": 1626235308116, "groupName": "WEi", "pictureCount": 1, "company": "\uc704\uc5d4\ud130\ud14c\uc778\uba3c\ud2b8", "birthDate": "1999/09/22", "bodyProfile": "181cm, 70kg, 260~265mm, B\ud615,", "oldName": "", "userId": "OWst8rT9GJNRuVUs94cWCL6srW92", "about": ""}, {"id": "QyfgRdZVmbrcLV2DaI0J", "pictureCount": 1, "gender": false, "groupName": "Rocket Punch", "createdAt": 1626235308116, "updatedAt": 1626235308116, "birthDate": "2003/08/14", "jobClass": "\uac00\uc218", "image": "https://touchizen.com/idolface/image/idolprofile/08_sohee_rocketpunch/1.jpg", "about": "", "oldName": "", "company": "\uc6b8\ub9bc \uc5d4\ud130\ud14c\uc778\uba3c\ud2b8", "userId": "OWst8rT9GJNRuVUs94cWCL6srW92", "bodyProfile": "159~160cm, 46kg, A\ud615, 235~240mm", "isApproved": true, "name": "\uc18c\ud76c"}, {"id": "WCZAP0oMFPltGZcQlbKu", "gender": false, "bodyProfile": "170.2cm, 52kg, A\ud615, 250mm", "about": "", "jobClass": "\uac00\uc218", "userId": "OWst8rT9GJNRuVUs94cWCL6srW92", "oldName": "", "updatedAt": 1626235308116, "pictureCount": 1, "isApproved": true, "birthDate": "2001/03/17", "name": "\uc218\uc724", "createdAt": 1626235308116, "image": "https://touchizen.com/idolface/image/idolprofile/10_sooyun_singer/1.jpg", "company": "\uc6b8\ub9bc \uc5d4\ud130\ud14c\uc778\uba3c\ud2b8", "groupName": "Rocket Punch"}, {"id": "ZU6pks7bbVbdu1pJTyFx", "image": "https://touchizen.com/idolface/image/idolprofile/34_jeongdongha_singer_actor/1.jpg", "gender": true, "jobClass": "\uac00\uc218, \ubba4\uc9c0\uceec\ubc30\uc6b0", "groupName": "", "name": "\uc815\ub3d9\ud558", "company": "\ubba4\uc9c1\uc6d0\ucef4\ud37c\ub2c8", "oldName": "", "about": "", "createdAt": 1626235308116, "bodyProfile": "178cm, 65kg, A\ud615", "updatedAt": 1626235308116, "isApproved": true, "birthDate": "1980/04/17", "userId": "OWst8rT9GJNRuVUs94cWCL6srW92", "pictureCount": 1}, {"id": "oZUx4lgKg4w99LF1ApkP", "name": "\uc774\ucc44\uc601", "birthDate": "2000/05/14", "groupName": "Fromis 9", "about": "", "gender": false, "userId": "OWst8rT9GJNRuVUs94cWCL6srW92", "image": "https://touchizen.com/idolface/image/idolprofile/14_leechaeyoung_fromis9/1.jpg", "jobClass": "\uac00\uc218", "isApproved": true, "updatedAt": 1626235308116, "createdAt": 1626235308116, "pictureCount": 1, "oldName": "", "bodyProfile": "169cm, 48kg, B\ud615", "company": "\uc624\ud504\ub354\ub808\ucf54\ub4dc \uc5d4\ud130\ud14c\uc778\uba3c\ud2b8"}, {"id": "xAGX1I33ZBlx7dk16EXn", "updatedAt": 1626235308116, "gender": false, "bodyProfile": "163cm, B\ud615", "company": "\uc6b8\ub9bc \uc5d4\ud130\ud14c\uc778\uba3c\ud2b8", "oldName": "", "birthDate": "2000/08/01", "jobClass": "\uac00\uc218", "createdAt": 1626235308116, "image": "https://touchizen.com/idolface/image/idolprofile/01_kimchaewon_izone/1.jpg", "groupName": "IZ*ONE", "isApproved": true, "name": "\uae40\ucc44\uc6d0", "pictureCount": 1, "userId": "OWst8rT9GJNRuVUs94cWCL6srW92", "about": ""}, {"id": "xl6o6WaOjL2IKnidH4AY", "groupName": "\uc5c5\ud150\uc158", "company": "\uc704\uc5d4\ud130\ud14c\uc778\uba3c\ud2b8", "isApproved": true, "pictureCount": 1, "userId": "OWst8rT9GJNRuVUs94cWCL6srW92", "birthDate": "1996/10/27", "updatedAt": 1626235308116, "image": "https://touchizen.com/idolface/image/idolprofile/23_kimwooseok_uptention/1.jpg", "jobClass": "\uac00\uc218", "name": "\uae40\uc6b0\uc11d", "gender": true, "bodyProfile": "173.5cm, 54kg, B\ud615, \uc0c1\uc758 100-105, \ud558\uc758 26-27, 250mm", "about": "", "oldName": "", "createdAt": 1626235308116}, {"id": "y3gzJN0MFxBF88mrJgP4", "about": "", "image": "https://touchizen.com/idolface/image/idolprofile/12_younkyoung_rocketpunch/1.jpg", "oldName": "", "birthDate": "2001/11/01", "isApproved": true, "name": "\uc724\uacbd", "pictureCount": 1, "updatedAt": 1626235308116, "bodyProfile": "158~9cm, 42~43kg, O\ud615, 240mm", "groupName": "Rocket Punch", "createdAt": 1626235308116, "userId": "OWst8rT9GJNRuVUs94cWCL6srW92", "company": "\uc6b8\ub9bc \uc5d4\ud130\ud14c\uc778\uba3c\ud2b8", "jobClass": "\uac00\uc218", "gender": false}, {"id": "oyzGHUgdWhJOESn9m7Ys", "gender": false, "birthDate": "1998/03/20", "name": "\ubc15\uc9c0\uc6d0", "createdAt": 1626235308116, "bodyProfile": "158cm, 44kg, A\ud615", "jobClass": "\uac00\uc218", "groupName": "Fromis 9", "company": "\uc624\ud504\ub354\ub808\ucf54\ub4dc \uc5d4\ud130\ud14c\uc778\uba3c\ud2b8", "pictureCount": 2, "updatedAt": 1626235308116, "image": "https://touchizen.com/idolface/image/idolprofile/06_parkjiwon_fromis9/1.jpg", "oldName": "", "isApproved": true, "about": "", "userId": "OWst8rT9GJNRuVUs94cWCL6srW92"}, {"id": "3AlzOs469WjBpdrTqc63", "company": "HYBE", "name": "\ubdd4", "pictureCount": 3, "about": "", "bodyProfile": "179cm, 63kg, AB\ud615, 275mm", "updatedAt": 1626235308116, "userId": "OWst8rT9GJNRuVUs94cWCL6srW92", "jobClass": "\uac00\uc218", "image": "https://touchizen.com/idolface/image/idolprofile/27_v_kimtaehyeong_bts/1.jpg", "birthDate": "1995/12/30", "gender": true, "groupName": "BTS", "isApproved": true, "oldName": "", "createdAt": 1626235308116}, {"id": "jwRAglOFem7lnD0PAVsg", "about": "", "image": "https://touchizen.com/idolface/image/idolprofile/07_seonmee_wondergirls/1.jpg", "isApproved": true, "gender": false, "createdAt": 1626235308116, "pictureCount": 3, "birthDate": "1992/05/02", "oldName": "", "groupName": "\uc6d0\ub354\uac78\uc2a4", "jobClass": "\uac00\uc218", "name": "\uc120\ubbf8", "company": "\uc5b4\ube44\uc2a4\ucef4\ud37c\ub2c8", "bodyProfile": "166cm, 50kg, AB\ud615", "updatedAt": 1626235308116, "userId": "OWst8rT9GJNRuVUs94cWCL6srW92"}, {"id": "sYTw5AauQPe54dSGENAA", "isApproved": true, "createdAt": 1626235308116, "oldName": "", "groupName": "WINNER", "company": "YG\uc5d4\ud130\ud14c\uc778\uba3c\ud2b8", "image": "https://touchizen.com/idolface/image/idolprofile/24_kimjinwoo_winner/1.jpg", "jobClass": "\uac00\uc218", "about": "", "gender": true, "pictureCount": 4, "updatedAt": 1626235308116, "userId": "OWst8rT9GJNRuVUs94cWCL6srW92", "bodyProfile": "176cm, 65kg, A\ud615", "birthDate": "1996/10/27", "name": "\uae40\uc9c4\uc6b0"}, {"id": "kG4b7aOUbPiRnF5Sn83K", "birthDate": "1997/12/27", "oldName": "", "createdAt": 1626235308116, "name": "\uc7a5\uaddc\ub9ac", "updatedAt": 1626235308116, "groupName": "Fromis 9", "isApproved": true, "userId": "OWst8rT9GJNRuVUs94cWCL6srW92", "bodyProfile": "168cm, 50kg, 240mm, B\ud615", "gender": false, "image": "https://touchizen.com/idolface/image/idolprofile/15_jangkyulee_fromis9/1.jpg", "about": "", "pictureCount": 5, "jobClass": "\uac00\uc218", "company": "\uc624\ud504\ub354\ub808\ucf54\ub4dc \uc5d4\ud130\ud14c\uc778\uba3c\ud2b8"}, {"id": "VpX819BFOK4N6v4VR6C2", "oldName": "", "name": "\uc194\uc9c0", "pictureCount": 6, "image": "https://touchizen.com/idolface/image/idolprofile/09_soljee_exid/1.jpg", "userId": "OWst8rT9GJNRuVUs94cWCL6srW92", "about": "", "createdAt": 1626235308116, "updatedAt": 1626235308116, "gender": false, "groupName": "EXID", "jobClass": "\uac00\uc218", "bodyProfile": "170cm, 50kg, O\ud615", "isApproved": true, "company": "\uc528\uc81c\uc2a4\uc5d4\ud130\ud14c\uc778\uba3c\ud2b8", "birthDate": "1989/01/10"}, {"id": "tvHRPJ4WjBSyR9027KPi", "name": "\uc544\uc774\uc720", "groupName": "", "pictureCount": 6, "oldName": "", "about": "", "gender": false, "updatedAt": 1626235308116, "userId": "OWst8rT9GJNRuVUs94cWCL6srW92", "createdAt": 1626235308116, "bodyProfile": "161.8cm, O\ud615, 225mm", "jobClass": "\uac00\uc218, \ubc30\uc6b0", "birthDate": "1993/05/16", "isApproved": true, "image": "https://touchizen.com/idolface/image/idolprofile/11_iyou_leejeeun_singer/1.jpg", "company": "\uc774\ub2f4 \uc5d4\ud130\ud14c\uc778\uba3c\ud2b8"}, {"id": "0lgGGwuSGensmUV7HoVE", "bodyProfile": "160cm, O\ud615, 230mm", "oldName": "", "userId": "OWst8rT9GJNRuVUs94cWCL6srW92", "isApproved": true, "name": "\uc9c0\ud6a8", "image": "https://touchizen.com/idolface/image/idolprofile/18_jeehyo_twice/1.jpg", "company": "JYP \uc5d4\ud130\ud14c\uc778\uba3c\ud2b8", "gender": false, "pictureCount": 7, "about": "", "birthDate": "1997/02/01", "jobClass": "\uac00\uc218", "createdAt": 1626235308116, "groupName": "Twice", "updatedAt": 1626235308116}, {"id": "hv3nK2nwAoSTPGsjeyDn", "bodyProfile": "163cm, 48kg, A\ud615, 250mm", "createdAt": 1626235308116, "name": "\ub098\uc5f0", "isApproved": true, "updatedAt": 1626235308116, "about": "\ub098\uc5f0\uc740 1995\ub144 9\uc6d4 22\uc77c \ub300\ud55c\ubbfc\uad6d \uc11c\uc6b8\ud2b9\ubcc4\uc2dc \uac15\ub3d9\uad6c \uc0c1\uc77c\ub3d9\uc5d0\uc11c \ud0dc\uc5b4\ub0ac\ub2e4. JYP \uc5d4\ud130\ud14c\uc778\uba3c\ud2b8\uc5d0\uc11c 5\ub144\uac04 \uc5f0\uc2b5\uc0dd \uc0dd\ud65c\uc744 \ud55c \ub4a4, 2015\ub144 10\uc6d4 20\uc77c \uac78\uadf8\ub8f9 \ud2b8\uc640\uc774\uc2a4\uc758 9\uba85\uc758 \uba64\ubc84 \uc911 \ud55c \uba85\uc73c\ub85c \ub370\ubdd4\ud588\ub2e4. \ud604\uc7ac \uac74\uad6d\ub300\ud559\uad50 \uc601\uc0c1\uc601\ud654\ud559\uacfc \ud734\ud559 \uc911\uc774\ub2e4.", "birthDate": "1995/09/22", "userId": "OWst8rT9GJNRuVUs94cWCL6srW92", "image": "https://touchizen.com/idolface/image/idolprofile/02_nayeon_twice/1.jpg", "company": "JYP \uc5d4\ud130\ud14c\uc778\uba3c\ud2b8", "oldName": "", "pictureCount": 7, "jobClass": "\uac00\uc218", "groupName": "Twice", "gender": false}, {"id": "5AzGIHsnaaJWed0eGW7t", "updatedAt": 1626235308116, "name": "\ub178\uc9c0\uc120", "birthDate": "1998/11/23", "pictureCount": 8, "bodyProfile": "158cm, 43kg, 220mm, B\ud615", "userId": "OWst8rT9GJNRuVUs94cWCL6srW92", "about": "", "createdAt": 1626235308116, "oldName": "", "isApproved": true, "gender": false, "image": "https://touchizen.com/idolface/image/idolprofile/03_nojiseon_fromis9/1.jpg", "jobClass": "\uac00\uc218", "company": "\uc624\ud504\ub354\ub808\ucf54\ub4dc \uc5d4\ud130\ud14c\uc778\uba3c\ud2b8", "groupName": "Fromis 9"}, {"id": "FPleC3ALDLaEA9nLqzrK", "image": "https://touchizen.com/idolface/image/idolprofile/37_jin_bts/1.jpg", "updatedAt": 1626235308116, "createdAt": 1626235308116, "about": "", "pictureCount": 19, "oldName": "", "bodyProfile": "178.3cm, 61kg, O\ud615, 265mm, \uc0c1\uc758 115", "isApproved": true, "company": "HYBE", "name": "\uc9c4", "userId": "OWst8rT9GJNRuVUs94cWCL6srW92", "gender": true, "birthDate": "1992/12/04", "groupName": "BTS", "jobClass": "\uac00\uc218"}, {"id": "HfDJSaTUVel11pQPD15O", "about": "", "updatedAt": 1626235308116, "birthDate": "1994/02/18", "oldName": "", "bodyProfile": "177cm, 59kg, A\ud615, 265mm", "groupName": "BTS", "pictureCount": 20, "image": "https://touchizen.com/idolface/image/idolprofile/35_jhop_bts/1.jpg", "gender": true, "createdAt": 1626235308116, "jobClass": "\uac00\uc218", "company": "HYBE", "name": "\uc81c\uc774\ud649", "userId": "OWst8rT9GJNRuVUs94cWCL6srW92", "isApproved": true}, {"id": "lYqztPRdWwurxIdwZ8nx", "groupName": "BTS", "company": "HYBE", "image": "https://touchizen.com/idolface/image/idolprofile/36_jeemin_bts/1.jpg", "createdAt": 1626235308116, "birthDate": "1995/10/13", "about": "", "pictureCount": 20, "updatedAt": 1626235308116, "bodyProfile": "174cm, 58kg, A\ud615, 265mm", "name": "\uc9c0\ubbfc", "oldName": "", "userId": "OWst8rT9GJNRuVUs94cWCL6srW92", "isApproved": true, "jobClass": "\uac00\uc218", "gender": true}, {"id": "Bx9l5CD9zyUHOtRxTQ4F", "bodyProfile": "181cm, 70kg, A\ud615", "gender": true, "groupName": "BTS", "image": "https://touchizen.com/idolface/image/idolprofile/20_rm_bts/1.jpg", "pictureCount": 21, "name": "RM", "about": "", "oldName": "", "isApproved": true, "birthDate": "1994/09/12", "userId": "OWst8rT9GJNRuVUs94cWCL6srW92", "updatedAt": 1626235308116, "company": "HYBE", "createdAt": 1626235308116, "jobClass": "\uac00\uc218"}, {"id": "wQoSP9bjhLFOn8YiTs1s", "birthDate": "1999/04/23", "isApproved": true, "oldName": "", "groupName": "Twice", "jobClass": "\uac00\uc218", "image": "https://touchizen.com/idolface/image/idolprofile/19_chaeyoung_twice/1.jpg", "company": "JYP \uc5d4\ud130\ud14c\uc778\uba3c\ud2b8", "updatedAt": 1626235308116, "about": "", "pictureCount": 23, "bodyProfile": "158.5cm, 46kg, B\ud615(Rh-), 235mm", "userId": "OWst8rT9GJNRuVUs94cWCL6srW92", "createdAt": 1626235308116, "name": "\ucc44\uc601", "gender": false}, {"id": "HaQLWf8d5zoRegdw9skK", "userId": "OWst8rT9GJNRuVUs94cWCL6srW92", "pictureCount": 31, "birthDate": "1997/09/01", "updatedAt": 1626235308116, "company": "HYBE", "groupName": "BTS", "isApproved": true, "about": "", "name": "\uc815\uad6d", "createdAt": 1626235308116, "bodyProfile": "174~6cm, 265mm, O\ud615", "oldName": "", "image": "https://touchizen.com/idolface/image/idolprofile/33_jeongkuk_bts/1.jpg", "jobClass": "\uac00\uc218", "gender": true}, {"id": "D8GimzfBqSPyjgSxa5m0", "birthDate": "1993/03/09", "createdAt": 1626235308116, "isApproved": true, "company": "HYBE", "jobClass": "\uac00\uc218", "pictureCount": 32, "about": "", "updatedAt": 1626235308116, "bodyProfile": "174cm, 57kg, O\ud615, 265mm", "oldName": "", "name": "\uc288\uac00", "groupName": "BTS", "image": "https://touchizen.com/idolface/image/idolprofile/28_sugar_bts/1.jpg", "userId": "OWst8rT9GJNRuVUs94cWCL6srW92", "gender": true}]